odoo/addons/fieldservice_isp_flow/README.rst
odoo/addons/fieldservice_isp_flow/__init__.py
odoo/addons/fieldservice_isp_flow/__manifest__.py
odoo/addons/fieldservice_isp_flow/data/fsm_stage.xml
odoo/addons/fieldservice_isp_flow/i18n/de.po
odoo/addons/fieldservice_isp_flow/i18n/es.po
odoo/addons/fieldservice_isp_flow/i18n/es_CL.po
odoo/addons/fieldservice_isp_flow/i18n/fieldservice_isp_flow.pot
odoo/addons/fieldservice_isp_flow/i18n/pt_BR.po
odoo/addons/fieldservice_isp_flow/models/__init__.py
odoo/addons/fieldservice_isp_flow/models/fsm_order.py
odoo/addons/fieldservice_isp_flow/readme/CONFIGURE.rst
odoo/addons/fieldservice_isp_flow/readme/CONTRIBUTORS.rst
odoo/addons/fieldservice_isp_flow/readme/CREDITS.rst
odoo/addons/fieldservice_isp_flow/readme/DESCRIPTION.rst
odoo/addons/fieldservice_isp_flow/readme/ROADMAP.rst
odoo/addons/fieldservice_isp_flow/readme/USAGE.rst
odoo/addons/fieldservice_isp_flow/static/description/icon.png
odoo/addons/fieldservice_isp_flow/static/description/index.html
odoo/addons/fieldservice_isp_flow/views/fsm_order.xml
odoo12_addon_fieldservice_isp_flow-12.0.1.1.1.dist-info/METADATA
odoo12_addon_fieldservice_isp_flow-12.0.1.1.1.dist-info/WHEEL
odoo12_addon_fieldservice_isp_flow-12.0.1.1.1.dist-info/top_level.txt
odoo12_addon_fieldservice_isp_flow-12.0.1.1.1.dist-info/RECORD
